vowels_cons/__init__.py
vowles_cons-0.1.dist-info/LICENCE.txt
vowles_cons-0.1.dist-info/METADATA
vowles_cons-0.1.dist-info/WHEEL
vowles_cons-0.1.dist-info/top_level.txt
vowles_cons-0.1.dist-info/RECORD
